addition_simple_package/__init__.py
addition_simple_package/addition.py
addition_simple_package-0.1.2.dist-info/METADATA
addition_simple_package-0.1.2.dist-info/WHEEL
addition_simple_package-0.1.2.dist-info/top_level.txt
addition_simple_package-0.1.2.dist-info/RECORD
