Metadata-Version: 2.4
Name: addition-simple-package
Version: 0.1.2
Summary: A simple Python package that adds up
Author: Yerly Sevan
Classifier: Programming Language :: Python :: 3
Classifier: Operating System :: OS Independent
Requires-Python: >=3.6
Dynamic: author
Dynamic: classifier
Dynamic: requires-python
Dynamic: summary
